Metadata-Version: 2.1
Name: modulos-em-python
Version: 0.0.1
Summary: projeto de modulos DIO
Home-page: https://github.com/Weverlin88/modulos_com_python
Author: Weverlin
Author-email: weverlin13@gmail.com
Requires-Python: >=3.8
